{
  "match_id": "WC2026_B_MD3_1",
  "round": "initial",
  "round_label": "初始预测",
  "timestamp": "2026-06-17T01:40:04.273362",
  "_internal": {
    "说明": "内部留痕，供追溯复盘",
    "n_agents": 7,
    "weighted_delta": 0.83,
    "p_a_win": 0.38,
    "p_draw": 0.36,
    "p_b_win": 0.26,
    "dimension_breakdown": [
      {
        "dimension": "F_tactical",
        "label": "战术对位",
        "a_score": 7.0,
        "b_score": 5.5,
        "delta": 1.5,
        "confidence": 7.0,
        "weight": 0.25,
        "key_factors": [
          "加拿大4-4-2对禁区弧顶保护不足，瑞士扎卡（具备远射能力）和恩博洛（肋部穿插）可直接利用此漏洞",
          "瑞士高位防线虽怕快速直塞，但加拿大4-4-2并非顶级纵向传球执行者，且缺少核心戴维斯状态未知，威胁度存疑",
          "瑞士阵型灵活（3-4-2-1），能通过中场人数优势压制加拿大双后腰，从而控制节奏",
          "从赔率来看，瑞士被明显看好（1.15 vs 2.5），市场认知与战术分析一致"
        ],
        "reasoning": "瑞士的远射与肋部直塞能力能精准打击加拿大4-4-2阵型对禁区弧顶保护的致命弱点，同时加拿大虽然能利用瑞士高位防线的空档，但其自身防守结构性问题更被瑞士技术型球员（如扎卡）专门克制。"
      },
      {
        "dimension": "E_context",
        "label": "情境压力",
        "a_score": 5.5,
        "b_score": 5.0,
        "delta": 0.5,
        "confidence": 4.0,
        "weight": 0.2,
        "key_factors": [
          "瑞士队近两场友谊赛1平1负无胜绩",
          "加拿大队在最近友谊赛2-0击败哥斯达黎加",
          "瑞士队核心扎卡和恩博洛状态推测良好但无具体确认"
        ],
        "reasoning": "瑞士队凭借扎卡和恩博洛的个人声誉在赔率上被看好，但近期战绩不佳且缺乏最新信息；加拿大队状态稍好但核心球员戴維斯有伤疑，双方实力接近。"
      },
      {
        "dimension": "G_dna",
        "label": "大赛DNA",
        "a_score": 5.0,
        "b_score": 5.0,
        "delta": 0.0,
        "confidence": 2.0,
        "weight": 0.18,
        "key_factors": [],
        "reasoning": "Error: 'str' object has no attribute 'get'"
      },
      {
        "dimension": "D_keyplayer",
        "label": "关键球员",
        "a_score": 5.5,
        "b_score": 5.5,
        "delta": 0.0,
        "confidence": 3.0,
        "weight": 0.15,
        "key_factors": [
          "瑞士核心Xhaka和Embolo无2026年6月具体状态更新",
          "加拿大核心Davies疑似伤病史但无当前确认",
          "双方均无赛前发布会或针对性战术信息"
        ],
        "reasoning": "缺乏扎卡、戴维斯等核心状态及伤停信息，仅凭赔率支持瑞士但无具体球员事实支撑。"
      },
      {
        "dimension": "B_chemistry",
        "label": "球队化学",
        "a_score": 5.0,
        "b_score": 5.0,
        "delta": 0.0,
        "confidence": 4.0,
        "weight": 0.08,
        "key_factors": [
          "瑞士和加拿大均无核心组合合作年限信息",
          "两队教练均已被确认但无系统磨合细节",
          "赔率偏差由实力导致而非化学反应"
        ],
        "reasoning": "缺乏具体集训时间、核心组合合作年限及内部氛围信息，两队化学反应无差异。"
      },
      {
        "dimension": "A_strength",
        "label": "绝对实力",
        "a_score": 7.0,
        "b_score": 5.5,
        "delta": 1.5,
        "confidence": 7.0,
        "weight": 0.07,
        "key_factors": [
          "瑞士拥有欧冠级门将组合（科贝尔+姆沃戈），加拿大门将来自美职联",
          "瑞士后防有阿坎吉（曼城）、R罗（都灵）等五大联赛主力，加拿大后防多为美职联/英冠球员",
          "瑞士中场有扎卡（勒沃库森核心），加拿大中场缺乏同等级组织者",
          "赔率显示瑞士胜赔1.15，远低于加拿大2.5，市场明确倾向瑞士"
        ],
        "reasoning": "瑞士在门将（科贝尔/姆沃戈）、后防（阿坎吉）和中场（扎卡）三个位置均高于加拿大对应球员档次，戴维斯虽为超级突破点但孤掌难鸣"
      },
      {
        "dimension": "C_form",
        "label": "近期状态",
        "a_score": 5.5,
        "b_score": 5.5,
        "delta": 0.0,
        "confidence": 5.0,
        "weight": 0.07,
        "key_factors": [
          "瑞士近5场仅1胜，且被弱旅科索沃逼平",
          "加拿大连续5场不败，近3场零失球防守出色",
          "加拿大核心戴维斯伤情不确定降低其进攻威胁"
        ],
        "reasoning": "瑞士赔率优势巨大但近期友谊赛表现不稳，加拿大防守稳固且连续5场不败，双方在赛前信息中状态差距不显著。"
      }
    ],
    "calibration_warning": false,
    "calibration_note": "",
    "judge_reasoning": "瑞士胜"
  },
  "output": {
    "说明": "对外展示到HTML",
    "prediction": "瑞士胜",
    "confidence": "中",
    "reasons": [
      "瑞士的战术纪律严明，扎卡在中场的调度和拦截是球队的节拍器，他能有效切断加拿大核心戴维斯的反击推进路线。",
      "加拿大防线的身高和对抗能力不足，瑞士前锋恩博洛依靠速度与身体冲击力，在定位球和反击中容易制造得分机会。",
      "瑞士大赛经验丰富，小组赛首战往往稳字当头，面对大赛舞台相对生涩的加拿大，控制节奏的能力更强。"
    ],
    "key_risk": "加拿大可能利用戴维斯和乔纳森·大卫的快速反击打穿瑞士身后，若瑞士久攻不下被偷一球，心态容易急躁。"
  },
  "actual_result": null
}